lunapi/__init__.py
lunapi/libfftw3-3.dll
lunapi/libfftw3f-3.dll
lunapi/libfftw3l-3.dll
lunapi/lunapi0.cp310-win_amd64.pyd
lunapi/lunapi0.cpp
lunapi/lunapi1.py
lunapi-1.4.0.dist-info/METADATA
lunapi-1.4.0.dist-info/WHEEL
lunapi-1.4.0.dist-info/licenses/LICENSE
lunapi-1.4.0.dist-info/RECORD
