Metadata-Version: 2.2
Name: lunapi
Version: 1.4.0
Summary: Python interface to the Luna toolset for sleep signal analysis
Keywords: Sleep,EEG,PSG,Luna,Signal processing
Author-Email: Shaun Purcell <smpurcell@bwh.harvard.edu>, Senthil Palanivelu <spalanivelu@mgh.harvard.edu>, Nataliia Kozhemiako <nkozhemiako@bwh.harvard.edu>
Maintainer-Email: Senthil Palanivelu <spalanivelu@mgh.harvard.edu>
Classifier: Development Status :: 4 - Beta
Classifier: Intended Audience :: Science/Research
Classifier: Topic :: Scientific/Engineering :: Bio-Informatics
Classifier: License :: OSI Approved :: GNU General Public License v3 (GPLv3)
Classifier: Framework :: Jupyter :: JupyterLab
Classifier: Natural Language :: English
Classifier: Programming Language :: Python :: 3.8
Classifier: Programming Language :: Python :: 3.9
Classifier: Programming Language :: Python :: 3.10
Classifier: Programming Language :: Python :: 3.11
Classifier: Programming Language :: Python :: 3.12
Classifier: Programming Language :: Python :: 3.13
Classifier: Programming Language :: Python :: 3.14
Project-URL: www, https://zzz.bwh.harvard.edu/luna
Project-URL: github, http://github.com/remnrem/luna-api
Requires-Python: >=3.9
Requires-Dist: pandas<3,>=2
Requires-Dist: numpy>=2
Requires-Dist: matplotlib<4.0,>=3
Requires-Dist: scipy<2,>=1
Requires-Dist: plotly<6,>=5
Requires-Dist: nbformat<6,>=5
Requires-Dist: ipywidgets<9,>=8
Requires-Dist: tqdm<5,>=4
Requires-Dist: requests<3,>=2
Requires-Dist: IPython
